uniprot_mcp/__init__.py
uniprot_mcp/__main__.py
uniprot_mcp/http_app.py
uniprot_mcp/obs.py
uniprot_mcp/prompts.py
uniprot_mcp/server.py
uniprot_mcp/adapters/__init__.py
uniprot_mcp/adapters/parsers.py
uniprot_mcp/adapters/uniprot_client.py
uniprot_mcp/models/__init__.py
uniprot_mcp/models/domain.py
uniprot_mcp_fastmcp-0.1.1.dist-info/licenses/LICENSE
uniprot_mcp_fastmcp-0.1.1.dist-info/METADATA
uniprot_mcp_fastmcp-0.1.1.dist-info/WHEEL
uniprot_mcp_fastmcp-0.1.1.dist-info/entry_points.txt
uniprot_mcp_fastmcp-0.1.1.dist-info/top_level.txt
uniprot_mcp_fastmcp-0.1.1.dist-info/RECORD
