Metadata-Version: 2.4
Name: uniprot-mcp-fastmcp
Version: 0.1.1
Summary: Model Context Protocol server that surfaces UniProtKB data as MCP resources, tools, and prompts.
Author-email: Jose Duarte <josepipe0909@gmail.com>
License-Expression: MIT
Project-URL: Homepage, https://github.com/fastmcp-me/uniprot-mcp#readme
Project-URL: Repository, https://github.com/fastmcp-me/uniprot-mcp.git
Project-URL: Issues, https://github.com/fastmcp-me/uniprot-mcp/issues
Keywords: mcp,uniprot,bioinformatics,llm,agent
Classifier: Development Status :: 4 - Beta
Classifier: Intended Audience :: Developers
Classifier: Programming Language :: Python :: 3
Classifier: Programming Language :: Python :: 3.11
Classifier: Programming Language :: Python :: 3.12
Classifier: Topic :: Scientific/Engineering :: Bio-Informatics
Requires-Python: >=3.11
License-File: LICENSE
Requires-Dist: httpx>=0.28.1
Requires-Dist: mcp[cli]>=1.19.0
Requires-Dist: pydantic>=2.12.3
Requires-Dist: starlette>=0.48.0
Requires-Dist: tenacity>=9.1.2
Requires-Dist: uvicorn>=0.38.0
Requires-Dist: prometheus-client>=0.20.0
Dynamic: license-file
